serializer/__init__.py
serializer/serializers/__init__.py
serializer/serializers/json_serializer.py
serializer/serializers/serializer_factory.py
serializer/serializers/serializer_interface.py
serializer/serializers/xml_serializer.py
serializer/utils/__init__.py
serializer/utils/constants.py
serializer/utils/converter.py
serializer/utils/utilities.py
serializer_json_xml-1.0.0.dist-info/METADATA
serializer_json_xml-1.0.0.dist-info/WHEEL
serializer_json_xml-1.0.0.dist-info/top_level.txt
serializer_json_xml-1.0.0.dist-info/RECORD
