Metadata-Version: 2.1
Name: serializer-json-xml
Version: 1.0.0
Summary: This is my first module
Author: max
Keywords: example python
